mopidy_hoerbert
