Metadata-Version: 1.1
Name: Mopidy-Hoerbert
Version: 0.1.1
Summary: Hoerbert
Home-page: https://github.com/mneuhaus/mopidy_hoerbert
Author: Marc Neuhaus
Author-email: apocalip@gmail.com
License: Apache License, Version 2.0
Platform: UNKNOWN
Classifier: Environment :: No Input/Output (Daemon)
Classifier: Intended Audience :: End Users/Desktop
Classifier: License :: OSI Approved :: Apache Software License
Classifier: Operating System :: OS Independent
Classifier: Programming Language :: Python :: 2
Classifier: Topic :: Multimedia :: Sound/Audio :: Players
